autolab/__init__.py
autolab/_entry_script.py
autolab/autolab.pdf
autolab/scan.py
autolab/version.txt
autolab/core/__init__.py
autolab/core/_create_shortcut.py
autolab/core/config.py
autolab/core/default_driver_utilities.py
autolab/core/devices.py
autolab/core/drivers.py
autolab/core/elements.py
autolab/core/gitdir.py
autolab/core/infos.py
autolab/core/paths.py
autolab/core/recorder.py
autolab/core/repository.py
autolab/core/server.py
autolab/core/utilities.py
autolab/core/variables.py
autolab/core/version_adapter.py
autolab/core/web.py
autolab/core/gui/GUI_about.py
autolab/core/gui/GUI_add_device.py
autolab/core/gui/GUI_driver_installer.py
autolab/core/gui/GUI_instances.py
autolab/core/gui/GUI_preferences.py
autolab/core/gui/GUI_slider.py
autolab/core/gui/GUI_utilities.py
autolab/core/gui/GUI_variables.py
autolab/core/gui/__init__.py
autolab/core/gui/controlcenter/__init__.py
autolab/core/gui/controlcenter/main.py
autolab/core/gui/controlcenter/thread.py
autolab/core/gui/controlcenter/treewidgets.py
autolab/core/gui/icons/__init__.py
autolab/core/gui/icons/action-icon.svg
autolab/core/gui/icons/add-icon.svg
autolab/core/gui/icons/autolab-icon.ico
autolab/core/gui/icons/autolab-icon.png
autolab/core/gui/icons/autolab-icon.svg
autolab/core/gui/icons/bool-icon.svg
autolab/core/gui/icons/bytes-icon.svg
autolab/core/gui/icons/config-icon.svg
autolab/core/gui/icons/copy-icon.svg
autolab/core/gui/icons/dataframe-icon.svg
autolab/core/gui/icons/disconnect-icon.svg
autolab/core/gui/icons/down-icon.svg
autolab/core/gui/icons/export-icon.svg
autolab/core/gui/icons/float-icon.svg
autolab/core/gui/icons/github-icon.svg
autolab/core/gui/icons/import-icon.svg
autolab/core/gui/icons/int-icon.svg
autolab/core/gui/icons/is-disable-icon.svg
autolab/core/gui/icons/is-enable-icon.svg
autolab/core/gui/icons/measure-icon.svg
autolab/core/gui/icons/monitor-icon.svg
autolab/core/gui/icons/ndarray-icon.svg
autolab/core/gui/icons/parameter-icon.svg
autolab/core/gui/icons/paste-icon.svg
autolab-2.0.3.dist-info/licenses/LICENSE
autolab-2.0.3.dist-info/METADATA
autolab-2.0.3.dist-info/WHEEL
autolab-2.0.3.dist-info/entry_points.txt
autolab-2.0.3.dist-info/top_level.txt
autolab-2.0.3.dist-info/RECORD
