Metadata-Version: 2.4
Name: autolab
Version: 2.0.3
Summary: Python package for scientific experiments interfacing and automation
Home-page: https://github.com/autolab-project/autolab
Author: Quentin Chateiller, Bruno Garbin, Jonathan Peltier, Mathieu Jeannin
Author-email: autolab-project@googlegroups.com
Maintainer: Jonathan Peltier & Mathieu Jeannin
Maintainer-email: autolab-project@googlegroups.com
License: GPL-3.0 license
Project-URL: Documentation, https://autolab.readthedocs.io/en/latest/
Project-URL: Repository, https://github.com/autolab-project/autolab.git
Project-URL: Bug Tracker, https://github.com/autolab-project/autolab/issues
Classifier: Programming Language :: Python :: 3
Classifier: Programming Language :: Python :: 3 :: Only
Classifier: Programming Language :: Python :: 3.6
Classifier: Programming Language :: Python :: 3.7
Classifier: Programming Language :: Python :: 3.8
Classifier: Programming Language :: Python :: 3.9
Classifier: Programming Language :: Python :: 3.10
Classifier: Programming Language :: Python :: 3.11
Classifier: Programming Language :: Python :: 3.12
Classifier: Operating System :: OS Independent
Requires-Python: >=3.6
License-File: LICENSE
Requires-Dist: numpy>=1.16
Requires-Dist: pandas>=0.24
Requires-Dist: pyvisa>=1.10
Requires-Dist: python-vxi11>=0.9
Requires-Dist: pyqtgraph
Requires-Dist: qtpy
Requires-Dist: requests
Requires-Dist: tqdm
Requires-Dist: comtypes
Provides-Extra: gui
Requires-Dist: PyQt5; extra == "gui"
Requires-Dist: pillow; extra == "gui"
Dynamic: home-page
Dynamic: license-file
Dynamic: maintainer
Dynamic: maintainer-email
Dynamic: requires-python
